roboherd/__init__.py
roboherd/__main__.py
roboherd/py.typed
roboherd/register.py
roboherd/test_validators.py
roboherd/util.py
roboherd/validators.py
roboherd/version.py
roboherd/annotations/__init__.py
roboherd/annotations/bovine.py
roboherd/annotations/common.py
roboherd/cow/__init__.py
roboherd/cow/const.py
roboherd/cow/handlers.py
roboherd/cow/profile.py
roboherd/cow/test_handlers.py
roboherd/cow/test_init.py
roboherd/cow/test_profile.py
roboherd/cow/test_util.py
roboherd/cow/types.py
roboherd/cow/util.py
roboherd/examples/__init__.py
roboherd/examples/dev_null.py
roboherd/examples/json_echo.py
roboherd/examples/meta.py
roboherd/examples/moocow.py
roboherd/examples/number.py
roboherd/examples/rooster.py
roboherd/examples/scarecrow.py
roboherd/herd/__init__.py
roboherd/herd/builder.py
roboherd/herd/processor.py
roboherd/herd/scheduler.py
roboherd/herd/test_herd.py
roboherd/herd/test_scheduler.py
roboherd/herd/types.py
roboherd/herd/manager/__init__.py
roboherd/herd/manager/config.py
roboherd/herd/manager/load.py
roboherd/herd/manager/test_config.py
roboherd/herd/manager/test_load.py
roboherd/herd/manager/test_manager.py
roboherd/testing/__init__.py
roboherd/testing/steps/__init__.py
roboherd/testing/steps/robocow.py
roboherd-0.1.13.dist-info/METADATA
roboherd-0.1.13.dist-info/WHEEL
roboherd-0.1.13.dist-info/entry_points.txt
roboherd-0.1.13.dist-info/RECORD
