Metadata-Version: 2.4
Name: roboherd
Version: 0.1.13
Summary: A Fediverse bot framework
Project-URL: Documentation, https://bovine.codeberg.page/roboherd/
Project-URL: Repository, https://codeberg.org/bovine/roboherd
Requires-Python: >=3.11
Requires-Dist: almabtrieb>=0.2
Requires-Dist: apscheduler>=3.11.0
Requires-Dist: click>=8.1.8
Requires-Dist: cron-descriptor>=1.4.5
Requires-Dist: dynaconf>=3.2.6
Requires-Dist: fast-depends>=3.0.0
Requires-Dist: pydantic==2.12.3
Requires-Dist: tomli-w>=1.1.0
Provides-Extra: amqp
Requires-Dist: almabtrieb[amqp]>=0.2.8; extra == 'amqp'
Provides-Extra: bovine
Requires-Dist: bovine>=0.5.15; extra == 'bovine'
Requires-Dist: markdown>=3.7; extra == 'bovine'
Provides-Extra: dev
Requires-Dist: aiohttp>=3.11.12; extra == 'dev'
Requires-Dist: watchfiles>=1.0.4; extra == 'dev'
Provides-Extra: mqtt
Requires-Dist: almabtrieb[mqtt]>=0.2.8; extra == 'mqtt'
